bluenet_logs/BluenetLogs.py
bluenet_logs/LogFormatter.py
bluenet_logs/LogLineRetriever.py
bluenet_logs/__init__.py
bluenet_logs-1.2.1.dist-info/METADATA
bluenet_logs-1.2.1.dist-info/WHEEL
bluenet_logs-1.2.1.dist-info/top_level.txt
bluenet_logs-1.2.1.dist-info/RECORD
