Metadata-Version: 2.1
Name: bluenet-logs
Version: 1.2.1
Summary: UNKNOWN
Home-page: https://github.com/crownstone/bluenet-lib-logs
Author: Crownstone B.V.
License: UNKNOWN
Platform: UNKNOWN
Classifier: Programming Language :: Python :: 3.7
Requires-Python: >=3.7
Requires-Dist: crownstone-uart (~=2.4)
